vwrt/.DS_Store
vwrt/__init__.py
vwrt/vwrt.py
vwrt-0.0.5.dist-info/entry_points.txt
vwrt-0.0.5.dist-info/WHEEL
vwrt-0.0.5.dist-info/METADATA
vwrt-0.0.5.dist-info/RECORD
