Metadata-Version: 2.1
Name: vwrt
Version: 0.0.5
Summary: Video Waste Reduction Tool: Automated video editing
Home-page: https://github.com/evnb/vwrt
License: MIT
Keywords: Ffmpeg,Accessibility,Video Editing,YouTube
Author: Evan Binder
Author-email: evanmbinder@gmail.com
Requires-Python: >=3.6,<4.0
Classifier: Environment :: Console
Classifier: Intended Audience :: Education
Classifier: Intended Audience :: End Users/Desktop
Classifier: License :: OSI Approved :: MIT License
Classifier: Programming Language :: Python :: 3
Classifier: Programming Language :: Python :: 3.6
Classifier: Programming Language :: Python :: 3.7
Classifier: Programming Language :: Python :: 3.8
Classifier: Programming Language :: Python :: 3.9
Classifier: Topic :: Multimedia
Classifier: Topic :: Multimedia :: Sound/Audio
Classifier: Topic :: Multimedia :: Video
Classifier: Topic :: Utilities
Requires-Dist: numpy (>=1.19.2,<1.20.0)
Project-URL: Repository, https://github.com/evnb/vwrt
